LICENSE
MANIFEST.in
README.md
setup.cfg
setup.py
tap_chargify/__init__.py
tap_chargify/chargify.py
tap_chargify/context.py
tap_chargify/discover.py
tap_chargify/streams.py
tap_chargify/sync.py
tap_chargify.egg-info/PKG-INFO
tap_chargify.egg-info/SOURCES.txt
tap_chargify.egg-info/dependency_links.txt
tap_chargify.egg-info/entry_points.txt
tap_chargify.egg-info/requires.txt
tap_chargify.egg-info/top_level.txt
tap_chargify/schemas/components.json
tap_chargify/schemas/coupons.json
tap_chargify/schemas/customers.json
tap_chargify/schemas/events.json
tap_chargify/schemas/invoices.json
tap_chargify/schemas/price_points.json
tap_chargify/schemas/product_families.json
tap_chargify/schemas/products.json
tap_chargify/schemas/statements.json
tap_chargify/schemas/subscriptions.json
tap_chargify/schemas/transactions.json