Metadata-Version: 2.1
Name: tap-chargify
Version: 0.0.8
Summary: Singer.io tap for extracting Chargify data
Home-page: http://github.com/singer-io/tap-chargify
Author: Stitch
License: UNKNOWN
Platform: UNKNOWN
Classifier: Programming Language :: Python :: 3 :: Only
Provides-Extra: dev
